{
  "collapse-filter": true,
  "search": "",
  "showTags": true,
  "showAttachments": false,
  "hideUnresolved": true,
  "showOrphans": false,
  "collapse-color-groups": true,
  "colorGroups": [
    {
      "query": "Hippocampus",
      "color": {
        "a": 1,
        "rgb": 16711680
      }
    },
    {
      "query": "tag:#idea",
      "color": {
        "a": 1,
        "rgb": 1966335
      }
    },
    {
      "query": "tag:#subject",
      "color": {
        "a": 1,
        "rgb": 5419488
      }
    },
    {
      "query": "tag:#methods",
      "color": {
        "a": 1,
        "rgb": 3926794
      }
    },
    {
      "query": "tag:#chemclass",
      "color": {
        "a": 1,
        "rgb": 16706064
      }
    },
    {
      "query": "tag:#chemtopic",
      "color": {
        "a": 1,
        "rgb": 49151
      }
    },
    {
      "query": "tag:#chemclassnotes",
      "color": {
        "a": 1,
        "rgb": 16756224
      }
    }
  ],
  "collapse-display": true,
  "showArrow": true,
  "textFadeMultiplier": -3,
  "nodeSizeMultiplier": 2.09554197229014,
  "lineSizeMultiplier": 1.47083333333333,
  "collapse-forces": true,
  "centerStrength": 0.386471067644662,
  "repelStrength": 14.1972290138549,
  "linkStrength": 0.224775876120619,
  "linkDistance": 103,
  "scale": 0.13690980359326818,
  "close": true
}